<messages>
<card_pink>Pink Playercard</card_pink>
<card_green>Green Playercard</card_green>
<card_blueGreen>BlueGreen Playercard</card_blueGreen>
<card_journalist>Journalist Playercard</card_journalist>
<card_yellow>Yellow Playercard</card_yellow>
<card_red>Red Playercard</card_red>
<card_blue>Blue Playercard</card_blue>
<card_grey>Grey Playercard</card_grey>


<body_ninjasuitpet>Ninja Pet</body_ninjasuitpet>
<body_present>Present Box</body_present>
<body_present_sock>Christmas Sock</body_present_sock>
<body_snowflake>Snowflake</body_snowflake>
<body_pumpkin>Pumpkin</body_pumpkin>
<body_ball>Clever Chlos</body_ball>
<body_alexCube>Cube Squared</body_alexCube>
<body_star>Shining Star</body_star>
<body_apple>Appetizing Apple</body_apple>


<chat_fusion>Fusion</chat_fusion>
<chat_orange>Orange</chat_orange>
</messages>